wg_interactive-0.6.3.dist-info/licenses/LICENSE
wginteractive/__init__.py
wginteractive/__main__.py
wginteractive/wginteractive.py
wginteractive/classes/__init__.py
wginteractive/classes/wginterface.py
wginteractive/classes/wgpeer.py
wginteractive/enums/clihandler_action.py
wginteractive/utility/__init__.py
wginteractive/utility/clihandler.py
wginteractive/utility/colorformatting.py
wginteractive/utility/iohandler.py
wginteractive/utility/serverinfo.py
wginteractive/utility/subprocesshandler.py
wginteractive/utility/systemd.py
wginteractive/utility/validation.py
wginteractive/utility/wghandler.py
wg_interactive-0.6.3.dist-info/METADATA
wg_interactive-0.6.3.dist-info/WHEEL
wg_interactive-0.6.3.dist-info/entry_points.txt
wg_interactive-0.6.3.dist-info/top_level.txt
wg_interactive-0.6.3.dist-info/RECORD
