Metadata-Version: 2.4
Name: wg-interactive
Version: 0.6.3
Summary: A cli utility for interactively modifying wireguard servers.
Author-email: Julian <mail@kaesebrot.eu>
Project-URL: Homepage, https://github.com/das-kaesebrot/wg-interactive
Project-URL: Bug Tracker, https://github.com/das-kaesebrot/wg-interactive/issues
Classifier: Programming Language :: Python :: 3
Classifier: Operating System :: OS Independent
Classifier: Development Status :: 4 - Beta
Classifier: Intended Audience :: System Administrators
Classifier: License :: OSI Approved :: GNU Affero General Public License v3 or later (AGPLv3+)
Classifier: Environment :: Console
Requires-Python: >=3.9
License-File: LICENSE
Requires-Dist: wgconfig==1.1.0
Requires-Dist: netifaces2==0.0.22
Dynamic: license-file
